aissemble_open_inference_protocol_kserve/__init__.py
aissemble_open_inference_protocol_kserve/aissemble_oip_kserve.py
aissemble_open_inference_protocol_kserve/kserve_dataplane.py
aissemble_open_inference_protocol_kserve/mappers/infer_mapper.py
aissemble_open_inference_protocol_kserve-1.1.0.dist-info/METADATA
aissemble_open_inference_protocol_kserve-1.1.0.dist-info/WHEEL
aissemble_open_inference_protocol_kserve-1.1.0.dist-info/licenses/LICENSE.txt
aissemble_open_inference_protocol_kserve-1.1.0.dist-info/RECORD
